[
 {
  "description": null, 
  "docstatus": 0, 
  "doctype": "FedEx Package", 
  "modified": "2016-11-10 20:05:03.088217", 
  "name": "PKG/001"
 }, 
 {
  "description": null, 
  "docstatus": 0, 
  "doctype": "FedEx Package", 
  "modified": "2016-11-10 20:06:43.995524", 
  "name": "PKG/002"
 }, 
 {
  "description": null, 
  "docstatus": 0, 
  "doctype": "FedEx Package", 
  "modified": "2016-11-10 20:06:44.337284", 
  "name": "PKG/003"
 }, 
 {
  "description": null, 
  "docstatus": 0, 
  "doctype": "FedEx Package", 
  "modified": "2016-11-10 20:06:44.340216", 
  "name": "PKG/004"
 }, 
 {
  "description": null, 
  "docstatus": 0, 
  "doctype": "FedEx Package", 
  "modified": "2016-11-10 20:06:44.343145", 
  "name": "PKG/005"
 }, 
 {
  "description": null, 
  "docstatus": 0, 
  "doctype": "FedEx Package", 
  "modified": "2016-11-10 20:06:44.346011", 
  "name": "PKG/006"
 }, 
 {
  "description": null, 
  "docstatus": 0, 
  "doctype": "FedEx Package", 
  "modified": "2016-11-10 20:06:44.348924", 
  "name": "PKG/007"
 }, 
 {
  "description": null, 
  "docstatus": 0, 
  "doctype": "FedEx Package", 
  "modified": "2016-11-10 20:06:44.352102", 
  "name": "PKG/008"
 }, 
 {
  "description": null, 
  "docstatus": 0, 
  "doctype": "FedEx Package", 
  "modified": "2016-11-10 20:06:44.354844", 
  "name": "PKG/009"
 }, 
 {
  "description": null, 
  "docstatus": 0, 
  "doctype": "FedEx Package", 
  "modified": "2016-11-10 20:06:44.357446", 
  "name": "PKG/010"
 }, 
 {
  "description": null, 
  "docstatus": 0, 
  "doctype": "FedEx Package", 
  "modified": "2016-11-10 20:06:44.360035", 
  "name": "PKG/011"
 }, 
 {
  "description": null, 
  "docstatus": 0, 
  "doctype": "FedEx Package", 
  "modified": "2016-11-10 20:06:44.362615", 
  "name": "PKG/012"
 }, 
 {
  "description": null, 
  "docstatus": 0, 
  "doctype": "FedEx Package", 
  "modified": "2016-11-10 20:06:44.365177", 
  "name": "PKG/013"
 }, 
 {
  "description": null, 
  "docstatus": 0, 
  "doctype": "FedEx Package", 
  "modified": "2016-11-10 20:06:44.367836", 
  "name": "PKG/014"
 }, 
 {
  "description": null, 
  "docstatus": 0, 
  "doctype": "FedEx Package", 
  "modified": "2016-11-10 20:06:44.370330", 
  "name": "PKG/015"
 }, 
 {
  "description": null, 
  "docstatus": 0, 
  "doctype": "FedEx Package", 
  "modified": "2016-11-10 20:06:44.372853", 
  "name": "PKG/016"
 }, 
 {
  "description": null, 
  "docstatus": 0, 
  "doctype": "FedEx Package", 
  "modified": "2016-11-10 20:06:44.375325", 
  "name": "PKG/017"
 }, 
 {
  "description": null, 
  "docstatus": 0, 
  "doctype": "FedEx Package", 
  "modified": "2016-11-10 20:06:44.377909", 
  "name": "PKG/018"
 }, 
 {
  "description": null, 
  "docstatus": 0, 
  "doctype": "FedEx Package", 
  "modified": "2016-11-10 20:06:44.380477", 
  "name": "PKG/019"
 }, 
 {
  "description": null, 
  "docstatus": 0, 
  "doctype": "FedEx Package", 
  "modified": "2016-11-10 20:06:44.383077", 
  "name": "PKG/020"
 }, 
 {
  "description": null, 
  "docstatus": 0, 
  "doctype": "FedEx Package", 
  "modified": "2016-11-10 20:06:44.385622", 
  "name": "PKG/021"
 }, 
 {
  "description": null, 
  "docstatus": 0, 
  "doctype": "FedEx Package", 
  "modified": "2016-11-10 20:06:44.388174", 
  "name": "PKG/022"
 }, 
 {
  "description": null, 
  "docstatus": 0, 
  "doctype": "FedEx Package", 
  "modified": "2016-11-10 20:06:44.390728", 
  "name": "PKG/023"
 }, 
 {
  "description": null, 
  "docstatus": 0, 
  "doctype": "FedEx Package", 
  "modified": "2016-11-10 20:06:44.393363", 
  "name": "PKG/024"
 }, 
 {
  "description": null, 
  "docstatus": 0, 
  "doctype": "FedEx Package", 
  "modified": "2016-11-10 20:06:44.396331", 
  "name": "PKG/025"
 }, 
 {
  "description": null, 
  "docstatus": 0, 
  "doctype": "FedEx Package", 
  "modified": "2016-11-10 20:06:44.399152", 
  "name": "PKG/026"
 }
]